data_mock/__init__.py
data_mock/exceptions.py
data_mock/requests.py
data_mock/google/cloud/bigquery/__init__.py
data_mock/google/cloud/bigquery/client.py
data_mock/google/cloud/bigquery/dataset.py
data_mock/google/cloud/bigquery/enums.py
data_mock/google/cloud/bigquery/exceptions.py
data_mock/google/cloud/bigquery/retry.py
data_mock/google/cloud/bigquery/schema.py
data_mock/google/cloud/bigquery/table.py
data_mock/google/cloud/bigquery/job/__init__.py
data_mock/google/cloud/bigquery/job/load.py
data_mock/google/cloud/bigquery/job/query.py
data_mock/google/cloud/storage/__init__.py
data_mock/google/cloud/storage/blob.py
data_mock/google/cloud/storage/bucket.py
data_mock/google/cloud/storage/client.py
data_mock/mock_helpers/generate_data.py
data_mock/mock_helpers/provider.py
data_mock/mock_helpers/writer.py
data_mock/psycopg2/__init__.py
data_mock/psycopg2/connect.py
data_mock/psycopg2/cursor.py
data_mock/psycopg2/ex.py
data_mock/psycopg2/exceptions.py
data_mock/psycopg2/extras.py
data_mock/requests_lib/__init__.py
data_mock/requests_lib/main.py
py_data_mock-0.0.16.dist-info/LICENSE
py_data_mock-0.0.16.dist-info/METADATA
py_data_mock-0.0.16.dist-info/WHEEL
py_data_mock-0.0.16.dist-info/top_level.txt
py_data_mock-0.0.16.dist-info/RECORD
