Metadata-Version: 2.1
Name: py-data-mock
Version: 0.0.16
Summary: Mock Data
Home-page: https://github.com/paulhtremblay/py-data-mock
Author: Henry Tremblay
Author-email: paulhtremblay@gmail.com
License: GNU GENERAL PUBLIC LICENSE
Classifier: Programming Language :: Python :: 3
Classifier: Topic :: Software Development :: Testing :: Mocking
License-File: LICENSE
